[
    {
        "version": "0.5",
        "description": {
            "Murder Mystery 2": [
                "Updated Trap Aura (Premium)",
                "Updated Reset Everyone (Premium)",
                "Updated Reset Murderer (Premium)",
                "Updated Reset Sheriff (Premium)",
                "Updated Glitch Everyone (Premium)",
                "Updated Glitch Murderer (Premium)",
                "Updated Glitch Sheriff (Premium)",
                "Updated Yeet Everyone (Premium)",
                "Updated Yeet Murderer (Premium)",
                "Updated Yeet Sheriff (Premium)",
                "Updated Silent Aim",
                "Updated Auto Farm",
                "Updated Instant Role Notify",
                "Updated Cham",
                "Updated Cham Dropped Gun",
                "Updated Cham Coins",
                "Updated ESP",
                "Updated ESP Dropped Gun",
                "Updated ESP Coins"
            ],
            "Blox Fruits": [
                "Updated Auto Farm",
                "Added Rip Indra Auto Farm Type",
                "Added Factory Auto Farm Type",
                "Added Saber Auto Farm Type",
                "Added Hallow Scythe Auto Farm Type",
                "Added Cake Queen Auto Farm Type",
                "Added Swan Glasses Auto Farm Type",
                "Added Rengoku Auto Farm Type",
                "Added Ectoplasm Auto Farm Type",
                "Added ESP Current Target",
                "Added Tracer Current Target",
                "Added Auto Buy Legendary Sword",
                "Added Auto Buy Random Fruits",
                "Added Auto Buy Microchip Law Boss",
                "Added Auto Buy Enchantment Color",
                "Added Auto Buy Dragon Talon",
                "Added Buy Gepo",
                "Added Buy Buso Haki",
                "Added Buy Soru",
                "Added Buy Observation Ken Haki",
                "Added Buy Black Leg",
                "Added Buy Electro",
                "Added Buy Fishman Karate",
                "Added Buy Dragon Claw",
                "Added Buy Superhuman",
                "Added Buy Death Step",
                "Added Buy Sharkman Karate",
                "Added Buy Electric Claw",
                "Added Buy Tragon Talon",
                "Added Buy Suprise",
                "Added Buy Stat Refund",
                "Added Buy Race Reroll",
                "Added Auto Ken Haki",
                "Added Auto Awakener",
                "Added Auto Grab Dropped Fruits",
                "Added Enable PVP",
                "Added Auto Enable PVP"
            ]
        }
    },
    {
        "version": "0.4",
        "description": {
            "Murder Mystery 2": [
                "Added Extra",
                "Updated Trap Aura (Premium)",
                "Updated Reset Everyone (Premium)",
                "Updated Reset Murderer (Premium)",
                "Updated Reset Sheriff (Premium)",
                "Updated Glitch Everyone (Premium)",
                "Updated Glitch Murderer (Premium)",
                "Updated Glitch Sheriff (Premium)",
                "Updated Yeet Everyone (Premium)",
                "Updated Yeet Murderer (Premium)",
                "Updated Yeet Sheriff (Premium)",
                "Updated Silent Aim",
                "Updated Auto Farm",
                "Updated Cham",
                "Updated Cham Dropped Gun",
                "Updated Cham Coins",
                "Updated ESP",
                "Updated ESP Dropped Gun",
                "Updated ESP Coins"
            ]
        }
    },
    {
        "version": "0.3",
        "description": {
            "Murder Mystery 2": [
                "Fixed grey esp in delta executor"
            ]
        }
    },
    {
        "version": "0.2",
        "description": {
            "Murder Mystery 2": [
                "Updated Infinite Spray Size (Premium)",
                "Updated Silent Aim"
            ],
            "Blox Fruits": [
                "Early Access",
                "Added Anti AFK (Premium)",
                "Added PVP Aimbot (Premium)",
                "Added Auto Farm Quests",
                "Added Auto Farm Chests",
                "Added Auto Farm Bones (Third Sea)",
                "Added Redeem All Valid Codes",
                "Added Join Pirates Team",
                "Added Join Marines Team",
                "Added Auto Upgrade Stats",
                "Added Teleport (First Sea, Second Sea, Third Sea)"
            ]
        }
    },
    {
        "version": "0.1",
        "description": {
            "Murder Mystery 2": [
                "New UI",
                "Added Click SFX"
            ]
        }
    }
]